ssi_empoorio_id/__init__.py
ssi_empoorio_id/cli.py
ssi_empoorio_id/client.py
ssi_empoorio_id/dashboard.py
ssi_empoorio_id/did.py
ssi_empoorio_id/exceptions.py
ssi_empoorio_id/presenter.py
ssi_empoorio_id/sdk.py
ssi_empoorio_id/utils.py
ssi_empoorio_id/vc.py
ssi_empoorio_id/verifier.py
ssi_empoorio_id-1.0.3.dist-info/licenses/LICENSE
ssi_empoorio_id-1.0.3.dist-info/METADATA
ssi_empoorio_id-1.0.3.dist-info/WHEEL
ssi_empoorio_id-1.0.3.dist-info/entry_points.txt
ssi_empoorio_id-1.0.3.dist-info/top_level.txt
ssi_empoorio_id-1.0.3.dist-info/RECORD
