Metadata-Version: 2.4
Name: ssi-empoorio-id
Version: 1.0.3
Summary: SSI Empoorio ID - Complete Self-Sovereign Identity SDK for Python
Home-page: https://github.com/empoorio/ssi-empoorio-id
Author: Empoorio Core Identity Team
Author-email: sdk@empoorio.id
Project-URL: Documentation, https://docs.empoorio.id/python-sdk
Project-URL: Source, https://github.com/empoorio/ssi-empoorio-id
Project-URL: Tracker, https://github.com/empoorio/ssi-empoorio-id/issues
Keywords: ssi self-sovereign-identity verifiable-credentials web3 blockchain biometric quantum-resistant
Classifier: Development Status :: 5 - Production/Stable
Classifier: Intended Audience :: Developers
Classifier: License :: OSI Approved :: MIT License
Classifier: Operating System :: OS Independent
Classifier: Programming Language :: Python :: 3
Classifier: Programming Language :: Python :: 3.8
Classifier: Programming Language :: Python :: 3.9
Classifier: Programming Language :: Python :: 3.10
Classifier: Programming Language :: Python :: 3.11
Classifier: Topic :: Security
Classifier: Topic :: Software Development :: Libraries :: Python Modules
Classifier: Topic :: Internet :: WWW/HTTP
Requires-Python: >=3.8
License-File: LICENSE
Requires-Dist: requests>=2.28.0
Requires-Dist: pydantic>=1.10.0
Requires-Dist: cryptography>=41.0.0
Requires-Dist: PyJWT>=2.6.0
Requires-Dist: python-dotenv>=1.0.0
Requires-Dist: click>=8.1.0
Requires-Dist: rich>=13.0.0
Requires-Dist: asyncio-mqtt>=0.13.0
Requires-Dist: websockets>=11.0.0
Provides-Extra: dev
Requires-Dist: pytest>=7.0.0; extra == "dev"
Requires-Dist: pytest-asyncio>=0.21.0; extra == "dev"
Requires-Dist: pytest-cov>=4.0.0; extra == "dev"
Requires-Dist: black>=22.0.0; extra == "dev"
Requires-Dist: isort>=5.10.0; extra == "dev"
Requires-Dist: flake8>=5.0.0; extra == "dev"
Requires-Dist: mypy>=1.0.0; extra == "dev"
Requires-Dist: sphinx>=5.0.0; extra == "dev"
Requires-Dist: sphinx-rtd-theme>=1.2.0; extra == "dev"
Provides-Extra: crypto
Requires-Dist: cryptography>=41.0.0; extra == "crypto"
Requires-Dist: pynacl>=1.5.0; extra == "crypto"
Provides-Extra: async
Requires-Dist: aiohttp>=3.8.0; extra == "async"
Requires-Dist: httpx>=0.24.0; extra == "async"
Provides-Extra: dashboard
Requires-Dist: rich>=13.0.0; extra == "dashboard"
Requires-Dist: click>=8.1.0; extra == "dashboard"
Requires-Dist: pyperclip>=1.8.0; extra == "dashboard"
Provides-Extra: all
Requires-Dist: pytest>=7.0.0; extra == "all"
Requires-Dist: pytest-asyncio>=0.21.0; extra == "all"
Requires-Dist: pytest-cov>=4.0.0; extra == "all"
Requires-Dist: black>=22.0.0; extra == "all"
Requires-Dist: isort>=5.10.0; extra == "all"
Requires-Dist: flake8>=5.0.0; extra == "all"
Requires-Dist: mypy>=1.0.0; extra == "all"
Requires-Dist: sphinx>=5.0.0; extra == "all"
Requires-Dist: sphinx-rtd-theme>=1.2.0; extra == "all"
Requires-Dist: cryptography>=41.0.0; extra == "all"
Requires-Dist: pynacl>=1.5.0; extra == "all"
Requires-Dist: aiohttp>=3.8.0; extra == "all"
Requires-Dist: httpx>=0.24.0; extra == "all"
Requires-Dist: rich>=13.0.0; extra == "all"
Requires-Dist: click>=8.1.0; extra == "all"
Requires-Dist: pyperclip>=1.8.0; extra == "all"
Dynamic: author
Dynamic: author-email
Dynamic: classifier
Dynamic: description
Dynamic: description-content-type
Dynamic: home-page
Dynamic: keywords
Dynamic: license-file
Dynamic: project-url
Dynamic: provides-extra
Dynamic: requires-dist
Dynamic: requires-python
Dynamic: summary
